action_dispatch/__init__.py
action_dispatch/action_dispatcher.py
action_dispatch/exceptions.py
action_dispatch-0.1.1.dist-info/METADATA
action_dispatch-0.1.1.dist-info/WHEEL
action_dispatch-0.1.1.dist-info/licenses/LICENSE
action_dispatch-0.1.1.dist-info/RECORD
