Metadata-Version: 2.4
Name: action-dispatch
Version: 0.1.1
Summary: A flexible action dispatching system with multi-dimensional routing capabilities
Project-URL: Homepage, https://github.com/eowl/action-dispatch
Project-URL: Documentation, https://action-dispatch.readthedocs.io
Project-URL: Repository, https://github.com/eowl/action-dispatch.git
Project-URL: Bug Tracker, https://github.com/eowl/action-dispatch/issues
Project-URL: Changelog, https://github.com/eowl/action-dispatch/blob/main/CHANGELOG.md
Author-email: eowl <eowl@me.com>
Maintainer-email: eowl <eowl@me.com>
License-Expression: MIT
License-File: LICENSE
Keywords: action,context-based,dispatch,framework,handler,middleware,multi-dimensional,routing
Classifier: Development Status :: 5 - Production/Stable
Classifier: Intended Audience :: Developers
Classifier: License :: OSI Approved :: MIT License
Classifier: Operating System :: OS Independent
Classifier: Programming Language :: Python :: 3
Classifier: Programming Language :: Python :: 3.9
Classifier: Programming Language :: Python :: 3.10
Classifier: Programming Language :: Python :: 3.11
Classifier: Programming Language :: Python :: 3.12
Classifier: Programming Language :: Python :: 3.13
Classifier: Topic :: Internet :: WWW/HTTP :: HTTP Servers
Classifier: Topic :: Software Development :: Libraries :: Application Frameworks
Classifier: Topic :: Software Development :: Libraries :: Python Modules
Classifier: Topic :: System :: Systems Administration
Classifier: Typing :: Typed
Requires-Python: >=3.9
Provides-Extra: dev
Requires-Dist: black>=22.0; extra == 'dev'
Requires-Dist: coverage>=7.0; extra == 'dev'
Requires-Dist: flake8>=5.0; extra == 'dev'
Requires-Dist: isort>=5.0; extra == 'dev'
Requires-Dist: mypy>=1.0; extra == 'dev'
Requires-Dist: pre-commit>=2.20; extra == 'dev'
Provides-Extra: docs
Requires-Dist: myst-parser>=0.18; extra == 'docs'
Requires-Dist: sphinx-rtd-theme>=1.0; extra == 'docs'
Requires-Dist: sphinx>=5.0; extra == 'docs'
